setup.py
Niff/__init__.py
Niff/agents.py
Niff/config.py
Niff/keyboard.py
Niff/lib.py
Niff/log.py
Niff/main.py
Niff/netlib.py
Niff/payloads.py
Niff/terminal.py
Niff.egg-info/PKG-INFO
Niff.egg-info/SOURCES.txt
Niff.egg-info/dependency_links.txt
Niff.egg-info/entry_points.txt
Niff.egg-info/not-zip-safe
Niff.egg-info/requires.txt
Niff.egg-info/top_level.txt