Metadata-Version: 1.0
Name: Niff
Version: 0.4
Summary: a tool
Home-page: https://github.com/Qingluan/.git
Author: Qing luan
Author-email: darkhackdevil@gmail.com
License: MIT
Platform: UNKNOWN
